sim_tools/__init__.py
sim_tools/_validation.py
sim_tools/datasets.py
sim_tools/distributions.py
sim_tools/output_analysis.py
sim_tools/time_dependent.py
sim_tools/trace.py
sim_tools/data/nspp_example1.csv
sim_tools/ovs/__init__.py
sim_tools/ovs/evaluation.py
sim_tools/ovs/fixed_budget.py
sim_tools/ovs/indifference_zone.py
sim_tools/ovs/toy_models.py
sim_tools-1.0.3.dist-info/METADATA
sim_tools-1.0.3.dist-info/WHEEL
sim_tools-1.0.3.dist-info/licenses/LICENSE
sim_tools-1.0.3.dist-info/RECORD
