Metadata-Version: 2.4
Name: sim-tools
Version: 1.0.3
Summary: Simulation Tools for Education and Practice
Project-URL: Homepage, https://github.com/sim-tools/sim-tools
Project-URL: Bug Tracker, https://github.com/sim-tools/sim-tools/issues
Project-URL: Documentation, https://sim-tools.github.io/sim-tools
Author-email: Thomas Monks <t.m.w.monks@exeter.ac.uk>, Amy Heather <A.Heather2@exeter.ac.uk>, Alison Harper <A.L.Harper@exeter.ac.uk>
License-Expression: MIT
License-File: LICENSE
Classifier: License :: OSI Approved :: MIT License
Classifier: Operating System :: OS Independent
Classifier: Programming Language :: Python :: 3.10
Classifier: Programming Language :: Python :: 3.11
Classifier: Programming Language :: Python :: 3.12
Classifier: Programming Language :: Python :: 3.13
Requires-Python: >=3.10
Requires-Dist: matplotlib>=3.1.3
Requires-Dist: numpy>=1.18.1
Requires-Dist: pandas>=2.0.0
Requires-Dist: plotly>=6.0.0
Requires-Dist: rich>=13.7.1
Requires-Dist: scikit-learn>=1.0.0
